CHANGELOG.md
LICENSE
README.md
nominal/__init__.py
nominal/__main__.py
nominal/nominal.py
nominal/py.typed
nominal/_utils/README.md
nominal/_utils/__init__.py
nominal/_utils/dataclass_tools.py
nominal/_utils/deprecation_tools.py
nominal/_utils/iterator_tools.py
nominal/_utils/streaming_tools.py
nominal/_utils/timing_tools.py
nominal/cli/__init__.py
nominal/cli/__main__.py
nominal/cli/attachment.py
nominal/cli/auth.py
nominal/cli/config.py
nominal/cli/dataset.py
nominal/cli/download.py
nominal/cli/mis.py
nominal/cli/run.py
nominal/cli/util/__init__.py
nominal/cli/util/click_log_handler.py
nominal/cli/util/global_decorators.py
nominal/cli/util/verify_connection.py
nominal/config/__init__.py
nominal/config/_config.py
nominal/core/__init__.py
nominal/core/_checklist_types.py
nominal/core/_clientsbunch.py
nominal/core/_constants.py
nominal/core/_event_types.py
nominal/core/_types.py
nominal/core/_video_types.py
nominal/core/asset.py
nominal/core/attachment.py
nominal/core/bounds.py
nominal/core/channel.py
nominal/core/checklist.py
nominal/core/client.py
nominal/core/connection.py
nominal/core/containerized_extractors.py
nominal/core/data_review.py
nominal/core/dataset.py
nominal/core/dataset_file.py
nominal/core/datasource.py
nominal/core/event.py
nominal/core/exceptions.py
nominal/core/filetype.py
nominal/core/log.py
nominal/core/run.py
nominal/core/secret.py
nominal/core/streaming_checklist.py
nominal/core/unit.py
nominal/core/user.py
nominal/core/video.py
nominal/core/video_file.py
nominal/core/workbook.py
nominal/core/workbook_template.py
nominal/core/workspace.py
nominal/core/_stream/__init__.py
nominal/core/_stream/batch_processor.py
nominal/core/_stream/batch_processor_proto.py
nominal/core/_stream/write_stream.py
nominal/core/_stream/write_stream_base.py
nominal/core/_utils/README.md
nominal/core/_utils/__init__.py
nominal/core/_utils/api_tools.py
nominal/core/_utils/multipart.py
nominal/core/_utils/multipart_downloader.py
nominal/core/_utils/networking.py
nominal-1.110.0.dist-info/METADATA
nominal-1.110.0.dist-info/WHEEL
nominal-1.110.0.dist-info/entry_points.txt
nominal-1.110.0.dist-info/licenses/LICENSE
nominal-1.110.0.dist-info/RECORD
